{
  "quiz_no": 250,
  "group": "C",
  "date": "2025-05-16",
  "songs": [
    {
      "order": 1,
      "contentId": "sm27896507",
      "answers": [
        {
          "user": "Abbey",
          "result": "OK"
        }
      ]
    },
    {
      "order": 2,
      "contentId": "sm17171418",
      "answers": [
        {
          "user": "とちこ",
          "result": "NG"
        },
        {
          "user": "よかずき",
          "result": "OK"
        }
      ]
    },
    {
      "order": 3,
      "contentId": "sm25994904",
      "answers": [
        {
          "user": "つみか",
          "result": "OK"
        }
      ]
    },
    {
      "order": 4,
      "contentId": "sm37462050",
      "answers": [
        {
          "user": "フリスク",
          "result": "OK"
        }
      ]
    },
    {
      "order": 5,
      "contentId": "sm40334799",
      "answers": [
        {
          "user": "とちこ",
          "result": "OK"
        }
      ]
    },
    {
      "order": 6,
      "contentId": "sm23032293",
      "answers": [
        {
          "user": "Abbey",
          "result": "OK"
        }
      ]
    },
    {
      "order": 7,
      "contentId": "sm40344350",
      "answers": [
        {
          "user": "フリスク",
          "result": "NG"
        },
        {
          "user": "",
          "result": "SKIP"
        }
      ]
    },
    {
      "order": 8,
      "contentId": "sm26997965",
      "answers": [
        {
          "user": "ぴーなっつ",
          "result": "OK"
        }
      ]
    },
    {
      "order": 9,
      "contentId": "sm32297705",
      "answers": [
        {
          "user": "",
          "result": "SKIP"
        }
      ]
    },
    {
      "order": 10,
      "contentId": "sm44674627",
      "answers": [
        {
          "user": "眠い人",
          "result": "OK"
        }
      ]
    },
    {
      "order": 11,
      "contentId": "sm36054608",
      "answers": [
        {
          "user": "Lyz",
          "result": "OK"
        }
      ]
    },
    {
      "order": 12,
      "contentId": "sm29014594",
      "answers": [
        {
          "user": "ぴーなっつ",
          "result": "OK"
        }
      ]
    },
    {
      "order": 13,
      "contentId": "sm18545819",
      "answers": [
        {
          "user": "",
          "result": "SKIP"
        }
      ]
    },
    {
      "order": 14,
      "contentId": "sm31807833",
      "answers": [
        {
          "user": "眠い人",
          "result": "OK"
        }
      ]
    },
    {
      "order": 15,
      "contentId": "sm17805004",
      "answers": [
        {
          "user": "",
          "result": "SKIP"
        }
      ]
    },
    {
      "order": 16,
      "contentId": "sm33960351",
      "answers": [
        {
          "user": "フリスク",
          "result": "NG"
        },
        {
          "user": "とちこ",
          "result": "OK"
        }
      ]
    },
    {
      "order": 17,
      "contentId": "sm25027572",
      "answers": [
        {
          "user": "ぽわ。",
          "result": "OK"
        }
      ]
    },
    {
      "order": 18,
      "contentId": "sm11631062",
      "answers": [
        {
          "user": "Abbey",
          "result": "OK"
        }
      ]
    },
    {
      "order": 19,
      "contentId": "sm42340907",
      "answers": [
        {
          "user": "よかずき",
          "result": "OK"
        }
      ]
    },
    {
      "order": 20,
      "contentId": "sm31835328",
      "answers": [
        {
          "user": "フリスク",
          "result": "OK"
        }
      ]
    },
    {
      "order": 21,
      "contentId": "sm13443184",
      "answers": [
        {
          "user": "わいえい",
          "result": "OK"
        }
      ]
    },
    {
      "order": 22,
      "contentId": "sm44681646",
      "answers": [
        {
          "user": "Lyz",
          "result": "NG"
        },
        {
          "user": "フリスク",
          "result": "OK"
        }
      ]
    },
    {
      "order": 23,
      "contentId": "sm29860605",
      "answers": [
        {
          "user": "",
          "result": "SKIP"
        }
      ]
    },
    {
      "order": 24,
      "contentId": "sm4092144",
      "answers": [
        {
          "user": "眠い人",
          "result": "OK"
        }
      ]
    },
    {
      "order": 25,
      "contentId": "sm21747941",
      "answers": [
        {
          "user": "",
          "result": "SKIP"
        }
      ]
    },
    {
      "order": 26,
      "contentId": "sm27389600",
      "answers": [
        {
          "user": "ぴーなっつ",
          "result": "NG"
        },
        {
          "user": "つみか",
          "result": "OK"
        }
      ]
    },
    {
      "order": 27,
      "contentId": "sm36967151",
      "answers": [
        {
          "user": "わいえい",
          "result": "NG"
        },
        {
          "user": "Lyz",
          "result": "OK"
        }
      ]
    },
    {
      "order": 28,
      "contentId": "sm1466832",
      "answers": [
        {
          "user": "Lyz",
          "result": "OK"
        }
      ]
    },
    {
      "order": 29,
      "contentId": "sm30756679",
      "answers": [
        {
          "user": "ぽわ。",
          "result": "NG"
        },
        {
          "user": "Lyz",
          "result": "NG"
        },
        {
          "user": "セレスト",
          "result": "NG"
        },
        {
          "user": "ぴーなっつ",
          "result": "NG"
        },
        {
          "user": "つみか",
          "result": "NG"
        },
        {
          "user": "Abbey",
          "result": "OK"
        }
      ]
    },
    {
      "order": 30,
      "contentId": "sm43837068",
      "answers": [
        {
          "user": "よかずき",
          "result": "OK"
        }
      ]
    },
    {
      "order": 31,
      "contentId": "sm24891870",
      "answers": [
        {
          "user": "よかずき",
          "result": "OK"
        }
      ]
    },
    {
      "order": 32,
      "contentId": "sm25872280",
      "answers": [
        {
          "user": "Lyz",
          "result": "OK"
        }
      ]
    },
    {
      "order": 33,
      "contentId": "sm31477166",
      "answers": [
        {
          "user": "わいえい",
          "result": "OK"
        }
      ]
    },
    {
      "order": 34,
      "contentId": "sm34777535",
      "answers": [
        {
          "user": "つみか",
          "result": "OK"
        }
      ]
    },
    {
      "order": 35,
      "contentId": "sm28268242",
      "answers": [
        {
          "user": "",
          "result": "SKIP"
        }
      ]
    },
    {
      "order": 36,
      "contentId": "sm26715301",
      "answers": [
        {
          "user": "つみか",
          "result": "OK"
        }
      ]
    },
    {
      "order": 37,
      "contentId": "sm22510890",
      "answers": [
        {
          "user": "",
          "result": "SKIP"
        }
      ]
    },
    {
      "order": 38,
      "contentId": "sm5463116",
      "answers": [
        {
          "user": "",
          "result": "SKIP"
        }
      ]
    },
    {
      "order": 39,
      "contentId": "sm16719809",
      "answers": [
        {
          "user": "とちこ",
          "result": "OK"
        }
      ]
    },
    {
      "order": 40,
      "contentId": "sm29494904",
      "answers": [
        {
          "user": "ぴーなっつ",
          "result": "NG"
        },
        {
          "user": "稲葉快晴",
          "result": "NG"
        },
        {
          "user": "",
          "result": "SKIP"
        }
      ]
    },
    {
      "order": 41,
      "contentId": "sm11224129",
      "answers": [
        {
          "user": "ぽわ。",
          "result": "OK"
        }
      ]
    },
    {
      "order": 42,
      "contentId": "sm40408445",
      "answers": [
        {
          "user": "わいえい",
          "result": "OK"
        }
      ]
    },
    {
      "order": 43,
      "contentId": "sm27771760",
      "answers": [
        {
          "user": "やま",
          "result": "OK"
        }
      ]
    },
    {
      "order": 44,
      "contentId": "sm38629132",
      "answers": [
        {
          "user": "とちこ",
          "result": "OK"
        }
      ]
    },
    {
      "order": 45,
      "contentId": "sm5432615",
      "answers": [
        {
          "user": "Lyz",
          "result": "WIN"
        }
      ]
    },
    {
      "order": 46,
      "contentId": "sm28753543",
      "answers": [
        {
          "user": "眠い人",
          "result": "OK"
        }
      ]
    },
    {
      "order": 47,
      "contentId": "sm43664035",
      "answers": [
        {
          "user": "よかずき",
          "result": "WIN"
        }
      ]
    },
    {
      "order": 48,
      "contentId": "sm6909505",
      "answers": [
        {
          "user": "フリスク",
          "result": "OK"
        }
      ]
    },
    {
      "order": 49,
      "contentId": "sm27258521",
      "answers": [
        {
          "user": "",
          "result": "SKIP"
        }
      ]
    },
    {
      "order": 50,
      "contentId": "nm11212356",
      "answers": [
        {
          "user": "ぴーなっつ",
          "result": "OK"
        }
      ]
    },
    {
      "order": 51,
      "contentId": "sm20191815",
      "answers": [
        {
          "user": "とちこ",
          "result": "WIN"
        }
      ]
    },
    {
      "order": 52,
      "contentId": "sm42309316",
      "answers": [
        {
          "user": "わいえい",
          "result": "OK"
        }
      ]
    },
    {
      "order": 53,
      "contentId": "sm24108252",
      "answers": [
        {
          "user": "わいえい",
          "result": "WIN"
        }
      ]
    },
    {
      "order": 54,
      "contentId": "sm44658591",
      "answers": [
        {
          "user": "",
          "result": "SKIP"
        }
      ]
    },
    {
      "order": 55,
      "contentId": "sm42463425",
      "answers": [
        {
          "user": "稲葉快晴",
          "result": "OK"
        }
      ]
    },
    {
      "order": 56,
      "contentId": "sm42554081",
      "answers": [
        {
          "user": "ぽわ。",
          "result": "OK"
        }
      ]
    },
    {
      "order": 57,
      "contentId": "sm33334184",
      "answers": [
        {
          "user": "ぽわ。",
          "result": "OK"
        }
      ]
    },
    {
      "order": 58,
      "contentId": "sm15255755",
      "answers": [
        {
          "user": "稲葉快晴",
          "result": "OK"
        }
      ]
    },
    {
      "order": 59,
      "contentId": "sm23134050",
      "answers": [
        {
          "user": "ぽわ。",
          "result": "WIN"
        }
      ]
    },
    {
      "order": 60,
      "contentId": "sm37643898",
      "answers": [
        {
          "user": "眠い人",
          "result": "WIN"
        }
      ]
    },
    {
      "order": 61,
      "contentId": "sm20503130",
      "answers": [
        {
          "user": "Abbey",
          "result": "WIN"
        }
      ]
    },
    {
      "order": 62,
      "contentId": "sm8598971",
      "answers": [
        {
          "user": "セレスト",
          "result": "OK"
        }
      ]
    },
    {
      "order": 63,
      "contentId": "sm21462040",
      "answers": [
        {
          "user": "",
          "result": "SKIP"
        }
      ]
    },
    {
      "order": 64,
      "contentId": "sm31098605",
      "answers": [
        {
          "user": "ぴーなっつ",
          "result": "OK"
        }
      ]
    },
    {
      "order": 65,
      "contentId": "sm31837608",
      "answers": [
        {
          "user": "",
          "result": "SKIP"
        }
      ]
    },
    {
      "order": 66,
      "contentId": "sm29651850",
      "answers": [
        {
          "user": "",
          "result": "SKIP"
        }
      ]
    },
    {
      "order": 67,
      "contentId": "sm39477058",
      "answers": [
        {
          "user": "稲葉快晴",
          "result": "OK"
        }
      ]
    },
    {
      "order": 68,
      "contentId": "sm43971315",
      "answers": [
        {
          "user": "フリスク",
          "result": "WIN"
        }
      ]
    },
    {
      "order": 69,
      "contentId": "sm43461213",
      "answers": [
        {
          "user": "稲葉快晴",
          "result": "OK"
        }
      ]
    },
    {
      "order": 70,
      "contentId": "sm41709913",
      "answers": [
        {
          "user": "稲葉快晴",
          "result": "WIN"
        }
      ]
    },
    {
      "order": 71,
      "contentId": "sm39053581",
      "answers": [
        {
          "user": "やま",
          "result": "OK"
        }
      ]
    },
    {
      "order": 72,
      "contentId": "sm18821036",
      "answers": [
        {
          "user": "やま",
          "result": "OK"
        }
      ]
    },
    {
      "order": 73,
      "contentId": "sm20504537",
      "answers": [
        {
          "user": "",
          "result": "SKIP"
        }
      ]
    },
    {
      "order": 74,
      "contentId": "sm40355503",
      "answers": [
        {
          "user": "ぴーなっつ",
          "result": "WIN"
        }
      ]
    }
  ]
}