{
  "quiz_no": 133,
  "group": "B",
  "date": "2022-11-12",
  "songs": [
    {
      "order": 1,
      "contentId": "sm36424703",
      "answers": [
        {
          "user": "ホワイト",
          "result": "OK"
        }
      ]
    },
    {
      "order": 2,
      "contentId": "sm29281205",
      "answers": [
        {
          "user": "すべから",
          "result": "OK"
        }
      ]
    },
    {
      "order": 3,
      "contentId": "sm20913914",
      "answers": [
        {
          "user": "Takuan",
          "result": "NG"
        },
        {
          "user": "yu-na*",
          "result": "NG"
        },
        {
          "user": "あー",
          "result": "OK"
        }
      ]
    },
    {
      "order": 4,
      "contentId": "sm11641089",
      "answers": [
        {
          "user": "chia*",
          "result": "OK"
        }
      ]
    },
    {
      "order": 5,
      "contentId": "sm34877912",
      "answers": [
        {
          "user": "Takuan",
          "result": "OK"
        }
      ]
    },
    {
      "order": 6,
      "contentId": "sm11524531",
      "answers": [
        {
          "user": "yu-na*",
          "result": "OK"
        }
      ]
    },
    {
      "order": 7,
      "contentId": "sm40389108",
      "answers": [
        {
          "user": "STN",
          "result": "OK"
        }
      ]
    },
    {
      "order": 8,
      "contentId": "sm30105817",
      "answers": [
        {
          "user": "すべから",
          "result": "OK"
        }
      ]
    },
    {
      "order": 9,
      "contentId": "sm15938820",
      "answers": [
        {
          "user": "Takuan",
          "result": "NG"
        },
        {
          "user": "ホワイト",
          "result": "OK"
        }
      ]
    },
    {
      "order": 10,
      "contentId": "sm35344830",
      "answers": [
        {
          "user": "chia*",
          "result": "OK"
        }
      ]
    },
    {
      "order": 11,
      "contentId": "sm38733911",
      "answers": [
        {
          "user": "fuji#",
          "result": "OK"
        }
      ]
    },
    {
      "order": 12,
      "contentId": "sm35203107",
      "answers": [
        {
          "user": "あー",
          "result": "NG"
        },
        {
          "user": "しるばー",
          "result": "OK"
        }
      ]
    },
    {
      "order": 13,
      "contentId": "sm6874320",
      "answers": [
        {
          "user": "Takuan",
          "result": "NG"
        },
        {
          "user": "",
          "result": "SKIP"
        }
      ]
    },
    {
      "order": 14,
      "contentId": "sm21604460",
      "answers": [
        {
          "user": "yu-na*",
          "result": "NG"
        },
        {
          "user": "ホワイト",
          "result": "NG"
        },
        {
          "user": "あー",
          "result": "OK"
        }
      ]
    },
    {
      "order": 15,
      "contentId": "sm26661454",
      "answers": [
        {
          "user": "あー",
          "result": "OK"
        }
      ]
    },
    {
      "order": 16,
      "contentId": "sm39569569",
      "answers": [
        {
          "user": "chia*",
          "result": "OK"
        }
      ]
    },
    {
      "order": 17,
      "contentId": "sm32320093",
      "answers": [
        {
          "user": "maruma",
          "result": "OK"
        }
      ]
    },
    {
      "order": 18,
      "contentId": "sm41107877",
      "answers": [
        {
          "user": "Takuan",
          "result": "NG"
        },
        {
          "user": "あー",
          "result": "NG"
        },
        {
          "user": "maruma",
          "result": "NG"
        },
        {
          "user": "STN",
          "result": "OK"
        }
      ]
    },
    {
      "order": 19,
      "contentId": "sm2393562",
      "answers": [
        {
          "user": "きぐな",
          "result": "OK"
        }
      ]
    },
    {
      "order": 20,
      "contentId": "sm25880040",
      "answers": [
        {
          "user": "きぐな",
          "result": "NG"
        },
        {
          "user": "maruma",
          "result": "OK"
        }
      ]
    },
    {
      "order": 21,
      "contentId": "sm32240815",
      "answers": [
        {
          "user": "chia*",
          "result": "NG"
        },
        {
          "user": "maruma",
          "result": "NG"
        },
        {
          "user": "あー",
          "result": "NG"
        },
        {
          "user": "ベガ",
          "result": "NG"
        },
        {
          "user": "たき火",
          "result": "OK"
        }
      ]
    },
    {
      "order": 22,
      "contentId": "sm36886350",
      "answers": [
        {
          "user": "すべから",
          "result": "OK"
        }
      ]
    },
    {
      "order": 23,
      "contentId": "sm38352936",
      "answers": [
        {
          "user": "fuji#",
          "result": "OK"
        }
      ]
    },
    {
      "order": 24,
      "contentId": "sm29397079",
      "answers": [
        {
          "user": "RRR",
          "result": "OK"
        }
      ]
    },
    {
      "order": 25,
      "contentId": "sm7021921",
      "answers": [
        {
          "user": "あー",
          "result": "WIN"
        }
      ]
    },
    {
      "order": 26,
      "contentId": "sm16036598",
      "answers": [
        {
          "user": "ホワイト",
          "result": "OK"
        }
      ]
    },
    {
      "order": 27,
      "contentId": "sm23151879",
      "answers": [
        {
          "user": "ベガ",
          "result": "NG"
        },
        {
          "user": "chia*",
          "result": "WIN"
        }
      ]
    },
    {
      "order": 28,
      "contentId": "sm38057729",
      "answers": [
        {
          "user": "Takuan",
          "result": "OK"
        }
      ]
    },
    {
      "order": 29,
      "contentId": "sm32914818",
      "answers": [
        {
          "user": "たき火",
          "result": "OK"
        }
      ]
    },
    {
      "order": 30,
      "contentId": "sm36967151",
      "answers": [
        {
          "user": "ベガ",
          "result": "NG"
        },
        {
          "user": "yu-na*",
          "result": "OK"
        }
      ]
    },
    {
      "order": 31,
      "contentId": "sm36406656",
      "answers": [
        {
          "user": "RRR",
          "result": "OK"
        }
      ]
    },
    {
      "order": 32,
      "contentId": "sm35789640",
      "answers": [
        {
          "user": "RRR",
          "result": "OK"
        }
      ]
    },
    {
      "order": 33,
      "contentId": "sm13136668",
      "answers": [
        {
          "user": "きぐな",
          "result": "OK"
        }
      ]
    },
    {
      "order": 34,
      "contentId": "sm8098201",
      "answers": [
        {
          "user": "まつせ",
          "result": "NG"
        },
        {
          "user": "maruma",
          "result": "NG"
        },
        {
          "user": "fuji#",
          "result": "NG"
        },
        {
          "user": "ホワイト",
          "result": "WIN"
        }
      ]
    },
    {
      "order": 35,
      "contentId": "so40825123",
      "answers": [
        {
          "user": "STN",
          "result": "OK"
        }
      ]
    },
    {
      "order": 36,
      "contentId": "sm39673644",
      "answers": [
        {
          "user": "STN",
          "result": "NG"
        },
        {
          "user": "fuji#",
          "result": "OK"
        }
      ]
    },
    {
      "order": 37,
      "contentId": "sm21153684",
      "answers": [
        {
          "user": "Cumber",
          "result": "NG"
        },
        {
          "user": "とげ",
          "result": "OK"
        }
      ]
    },
    {
      "order": 38,
      "contentId": "sm33842568",
      "answers": [
        {
          "user": "fuji#",
          "result": "WIN"
        }
      ]
    },
    {
      "order": 39,
      "contentId": "sm10700738",
      "answers": [
        {
          "user": "maruma",
          "result": "NG"
        },
        {
          "user": "まつせ",
          "result": "NG"
        },
        {
          "user": "STN",
          "result": "NG"
        },
        {
          "user": "きぐな",
          "result": "OK"
        }
      ]
    },
    {
      "order": 40,
      "contentId": "sm1249071",
      "answers": [
        {
          "user": "すべから",
          "result": "WIN"
        }
      ]
    },
    {
      "order": 41,
      "contentId": "sm5992615",
      "answers": [
        {
          "user": "Takuan",
          "result": "OK"
        }
      ]
    },
    {
      "order": 42,
      "contentId": "sm37301259",
      "answers": [
        {
          "user": "Takuan",
          "result": "WIN"
        }
      ]
    },
    {
      "order": 43,
      "contentId": "sm30989784",
      "answers": [
        {
          "user": "きぐな",
          "result": "WIN"
        }
      ]
    },
    {
      "order": 44,
      "contentId": "sm19940497",
      "answers": [
        {
          "user": "yu-na*",
          "result": "OK"
        }
      ]
    },
    {
      "order": 45,
      "contentId": "sm42734381",
      "answers": [
        {
          "user": "STN",
          "result": "WIN"
        }
      ]
    },
    {
      "order": 46,
      "contentId": "sm35140931",
      "answers": [
        {
          "user": "しるばー",
          "result": "OK"
        }
      ]
    },
    {
      "order": 47,
      "contentId": "sm8573139",
      "answers": [
        {
          "user": "yu-na*",
          "result": "NG"
        },
        {
          "user": "",
          "result": "SKIP"
        }
      ]
    },
    {
      "order": 48,
      "contentId": "sm36723442",
      "answers": [
        {
          "user": "maruma",
          "result": "OK"
        }
      ]
    },
    {
      "order": 49,
      "contentId": "sm35880454",
      "answers": [
        {
          "user": "Cumber",
          "result": "OK"
        }
      ]
    },
    {
      "order": 50,
      "contentId": "sm29548623",
      "answers": [
        {
          "user": "とげ",
          "result": "OK"
        }
      ]
    },
    {
      "order": 51,
      "contentId": "sm40215522",
      "answers": [
        {
          "user": "Cumber",
          "result": "OK"
        }
      ]
    },
    {
      "order": 52,
      "contentId": "sm35546354",
      "answers": [
        {
          "user": "たき火",
          "result": "OK"
        }
      ]
    },
    {
      "order": 53,
      "contentId": "sm8824375",
      "answers": [
        {
          "user": "Cumber",
          "result": "NG"
        },
        {
          "user": "yu-na*",
          "result": "NG"
        },
        {
          "user": "",
          "result": "SKIP"
        }
      ]
    },
    {
      "order": 54,
      "contentId": "sm31825017",
      "answers": [
        {
          "user": "まつせ",
          "result": "OK"
        }
      ]
    },
    {
      "order": 55,
      "contentId": "sm29182723",
      "answers": [
        {
          "user": "ベガ",
          "result": "OK"
        }
      ]
    },
    {
      "order": 56,
      "contentId": "sm23826634",
      "answers": [
        {
          "user": "ベガ",
          "result": "NG"
        },
        {
          "user": "とげ",
          "result": "OK"
        }
      ]
    },
    {
      "order": 57,
      "contentId": "sm31084095",
      "answers": [
        {
          "user": "Cumber",
          "result": "OK"
        }
      ]
    },
    {
      "order": 58,
      "contentId": "sm4748812",
      "answers": [
        {
          "user": "まつせ",
          "result": "NG"
        },
        {
          "user": "maruma",
          "result": "WIN"
        }
      ]
    },
    {
      "order": 59,
      "contentId": "sm30376326",
      "answers": [
        {
          "user": "Cumber",
          "result": "WIN"
        }
      ]
    },
    {
      "order": 60,
      "contentId": "sm16973327",
      "answers": [
        {
          "user": "たき火",
          "result": "WIN"
        }
      ]
    },
    {
      "order": 61,
      "contentId": "sm31363987",
      "answers": [
        {
          "user": "",
          "result": "SKIP"
        }
      ]
    },
    {
      "order": 62,
      "contentId": "sm7904669",
      "answers": [
        {
          "user": "しるばー",
          "result": "OK"
        }
      ]
    },
    {
      "order": 63,
      "contentId": "sm24909819",
      "answers": [
        {
          "user": "RRR",
          "result": "WIN"
        }
      ]
    },
    {
      "order": 64,
      "contentId": "sm11323864",
      "answers": [
        {
          "user": "しるばー",
          "result": "WIN"
        }
      ]
    },
    {
      "order": 65,
      "contentId": "sm30862689",
      "answers": [
        {
          "user": "",
          "result": "SKIP"
        }
      ]
    },
    {
      "order": 66,
      "contentId": "sm36036629",
      "answers": [
        {
          "user": "yu-na*",
          "result": "WIN"
        }
      ]
    },
    {
      "order": 67,
      "contentId": "sm33557234",
      "answers": [
        {
          "user": "まつせ",
          "result": "OK"
        }
      ]
    },
    {
      "order": 68,
      "contentId": "sm12252387",
      "answers": [
        {
          "user": "",
          "result": "SKIP"
        }
      ]
    },
    {
      "order": 69,
      "contentId": "sm36693297",
      "answers": [
        {
          "user": "ベガ",
          "result": "OK"
        }
      ]
    },
    {
      "order": 70,
      "contentId": "sm6666016",
      "answers": [
        {
          "user": "ベガ",
          "result": "OK"
        }
      ]
    },
    {
      "order": 71,
      "contentId": "sm30196130",
      "answers": [
        {
          "user": "とげ",
          "result": "WIN"
        }
      ]
    },
    {
      "order": 72,
      "contentId": "sm14120872",
      "answers": [
        {
          "user": "",
          "result": "SKIP"
        }
      ]
    },
    {
      "order": 73,
      "contentId": "sm39398775",
      "answers": [
        {
          "user": "まつせ",
          "result": "NG"
        },
        {
          "user": "",
          "result": "SKIP"
        }
      ]
    },
    {
      "order": 74,
      "contentId": "sm21652882",
      "answers": [
        {
          "user": "",
          "result": "SKIP"
        }
      ]
    },
    {
      "order": 75,
      "contentId": "sm23377561",
      "answers": [
        {
          "user": "",
          "result": "SKIP"
        }
      ]
    },
    {
      "order": 76,
      "contentId": "sm23335827",
      "answers": [
        {
          "user": "",
          "result": "SKIP"
        }
      ]
    },
    {
      "order": 77,
      "contentId": "sm28694937",
      "answers": [
        {
          "user": "ベガ",
          "result": "WIN"
        }
      ]
    },
    {
      "order": 78,
      "contentId": "sm33447553",
      "answers": [
        {
          "user": "",
          "result": "SKIP"
        }
      ]
    },
    {
      "order": 79,
      "contentId": "sm22294993",
      "answers": [
        {
          "user": "",
          "result": "SKIP"
        }
      ]
    },
    {
      "order": 80,
      "contentId": "sm17599064",
      "answers": [
        {
          "user": "",
          "result": "SKIP"
        }
      ]
    },
    {
      "order": 81,
      "contentId": "sm12589203",
      "answers": [
        {
          "user": "まつせ",
          "result": "OK"
        }
      ]
    },
    {
      "order": 82,
      "contentId": "sm33575428",
      "answers": [
        {
          "user": "",
          "result": "SKIP"
        }
      ]
    },
    {
      "order": 83,
      "contentId": "sm31394907",
      "answers": [
        {
          "user": "まつせ",
          "result": "WIN"
        }
      ]
    }
  ]
}