{
  "song": "infection waves",
  "contentId": "nm12831187",
  "title": "infection waves / 初音ミクオリジナル",
  "commentCounter": 2666,
  "lengthSeconds": 234,
  "likeCounter": 61,
  "mylistCounter": 4611,
  "rank": 423,
  "startTime": "2010-11-23T05:42:17+09:00",
  "thumbnailUrl": "https://nicovideo.cdn.nimg.jp/thumbnails/12831187/12831187",
  "userId": 532877,
  "viewCounter": 126517,
  "artist": [
    "sleepless"
  ],
  "tags": [
    "VOCALOID",
    "ミクオリジナル曲",
    "初音ミク",
    "ケチャップ",
    "infection_waves",
    "てへっ♪",
    "sleepless",
    "VOCALOID外国語曲リンク",
    "VOCALOID殿堂入り",
    "ヘッドホン推奨",
    "ミクノポップ"
  ],
  "channelId": null
}