{
  "song": "全てのVOC@LOIDに宣戦布告",
  "contentId": "sm11118039",
  "title": "【健音】全てのVOC@LOIDに宣戦布告【テイ】",
  "commentCounter": 12598,
  "lengthSeconds": 353,
  "likeCounter": 109,
  "mylistCounter": 4231,
  "rank": 460,
  "startTime": "2010-06-19T22:12:06+09:00",
  "thumbnailUrl": "https://nicovideo.cdn.nimg.jp/thumbnails/11118039/11118039",
  "userId": 328782,
  "viewCounter": 190857,
  "artist": [
    "ミナツキトーカ"
  ],
  "tags": [
    "音楽",
    "健音テイ",
    "全てのVOC@LOIDに宣戦布告",
    "UTAU殿堂入り",
    "UTAU",
    "UTAUオリジナル曲",
    "テイオリジナル曲",
    "パンドリストP",
    "ヤンデロイド",
    "VOCALOID",
    "UTAUイメージソング"
  ],
  "channelId": null
}