{
  "song": "護法少女ソワカちゃん",
  "contentId": "sm1235394",
  "title": "【初音ミク】護法少女ソワカちゃん【オリジナル】",
  "commentCounter": 6072,
  "lengthSeconds": 190,
  "likeCounter": 299,
  "mylistCounter": 4914,
  "rank": 342,
  "startTime": "2007-10-08T22:41:21+09:00",
  "thumbnailUrl": "https://nicovideo.cdn.nimg.jp/thumbnails/1235394/1235394",
  "userId": 517132,
  "viewCounter": 352420,
  "artist": [
    "kihirohito"
  ],
  "tags": [
    "音楽",
    "kihirohitop",
    "初音ミク",
    "ミクオリジナル曲",
    "護法少女ソワカちゃん",
    "VOCALOID殿堂入り",
    "VOCALOID仏堂入り",
    "JOYSOUND配信中",
    "VOCALOID"
  ],
  "channelId": null
}