{
  "song": "上から目線",
  "contentId": "sm13204472",
  "title": "【巡音ルカ】 上から目線 【オリジナル】",
  "startTime": "2011-01-03T12:07:23+09:00",
  "userId": 2303203,
  "thumbnailUrl": "https://nicovideo.cdn.nimg.jp/thumbnails/13204472/13204472",
  "viewCounter": 197851,
  "mylistCounter": 5302,
  "likeCounter": 17,
  "commentCounter": 13485,
  "lengthSeconds": 265,
  "artist": [
    "ぶりる"
  ],
  "tags": [
    "VOCALOID",
    "ルカオリジナル曲",
    "ぶりるP",
    "上から目線（ぶりる）",
    "巡音ルカ",
    "VOCALOID殿堂入り",
    "VOCAROCK"
  ],
  "channelId": null,
  "rank": 407
}