{
  "song": "桃色バニラ",
  "contentId": "sm13340169",
  "title": "【初音ミク】桃色バニラ【オリジナル】",
  "commentCounter": 545,
  "lengthSeconds": 262,
  "likeCounter": 4,
  "mylistCounter": 978,
  "rank": 1374,
  "startTime": "2011-01-18T09:47:05+09:00",
  "thumbnailUrl": "https://nicovideo.cdn.nimg.jp/thumbnails/13340169/13340169",
  "userId": 4888462,
  "viewCounter": 17876,
  "artist": [
    "らいおお"
  ],
  "tags": [
    "VOCALOID",
    "初音ミク",
    "ミクオリジナル曲",
    "桃色バニラ",
    "かわいいミクうた",
    "ミクノポップ",
    "もっと評価されるべき",
    "ボカランED曲",
    "らいおお"
  ],
  "channelId": null
}