{
  "song": "Bad ∞ End ∞ Night",
  "contentId": "sm16702635",
  "title": "【ボカロ8人】Bad ∞ End ∞ Night【オリジナル】",
  "startTime": "2012-01-15T18:30:38+09:00",
  "userId": 3397653,
  "thumbnailUrl": "https://nicovideo.cdn.nimg.jp/thumbnails/16702635/16702635",
  "viewCounter": 4826278,
  "mylistCounter": 91870,
  "likeCounter": 5722,
  "commentCounter": 71544,
  "lengthSeconds": 252,
  "artist": [
    "ひとしずく",
    "やま△"
  ],
  "tags": [
    "VOCALOID",
    "ひとしずくP",
    "やま△",
    "鈴ノ助",
    "TSO(とさお)",
    "Bad_∞_End_∞_Night",
    "VOCALOIDオリジナル曲",
    "VOCALOID空想童話曲リンク",
    "VOCALOID伝説入り",
    "DAM&JOY配信中"
  ],
  "channelId": null,
  "rank": 9
}