{
  "song": "しゃぼんのサラマンドラ",
  "contentId": "sm19980019",
  "title": "【KAITO】オリジナル曲「しゃぼんのサラマンドラ」【兄さん10人前】",
  "commentCounter": 6705,
  "lengthSeconds": 321,
  "likeCounter": 495,
  "mylistCounter": 7252,
  "rank": 242,
  "startTime": "2013-02-02T18:47:56+09:00",
  "thumbnailUrl": "https://nicovideo.cdn.nimg.jp/thumbnails/19980019/19980019",
  "userId": 259018,
  "viewCounter": 235218,
  "artist": [
    "ぶっちぎりP"
  ],
  "tags": [
    "VOCALOID",
    "KAITO",
    "Vocalosensation収録曲",
    "ぶっちぎりP",
    "KAITOオリジナル曲",
    "うむ",
    "VOCALOID殿堂入り",
    "KAITO名曲リンク",
    "しゃぼんのサラマンドラ",
    "神調教",
    "爽やかなぼかうた"
  ],
  "channelId": null
}