{
  "song": "鼓膜",
  "contentId": "sm20288269",
  "title": "【初音ミク】鼓膜【オリジナル曲】",
  "commentCounter": 847,
  "lengthSeconds": 250,
  "likeCounter": 115,
  "mylistCounter": 2263,
  "rank": 642,
  "startTime": "2013-03-09T21:56:37+09:00",
  "thumbnailUrl": "https://nicovideo.cdn.nimg.jp/thumbnails/20288269/20288269",
  "userId": 13053833,
  "viewCounter": 82310,
  "artist": [
    "宮沢もよよ"
  ],
  "tags": [
    "VOCALOID",
    "宮沢もよよ",
    "あさぎり",
    "QUADROPHENIA",
    "鼓膜(宮沢もよよ)",
    "初音ミク",
    "ミクオリジナル曲",
    "春ニカ祭2013",
    "ミクトロニカ",
    "VOCALOID_Professional_2013_feat.初音ミク",
    "ミクの日2013"
  ],
  "channelId": null
}