{
  "song": "ペンシル・デイズ",
  "contentId": "sm20403611",
  "title": "塾講師なので本気出して卒業ソングをつくってみたよ【初音ミク など】",
  "commentCounter": 8317,
  "lengthSeconds": 304,
  "likeCounter": 73,
  "mylistCounter": 11463,
  "rank": 140,
  "startTime": "2013-03-22T18:32:26+09:00",
  "thumbnailUrl": "https://nicovideo.cdn.nimg.jp/thumbnails/20403611/20403611",
  "userId": 20345306,
  "viewCounter": 447142,
  "artist": [
    "黒田亜津"
  ],
  "tags": [
    "VOCALOID",
    "投稿者コメント",
    "黒田亜津",
    "初音ミク",
    "ペンシル・デイズ",
    "VOCALOID卒業曲集",
    "VOCALOID合唱団",
    "VOCALOID殿堂入り",
    "vocaloidオリジナル曲",
    "良調教",
    "VOCALOID合唱曲"
  ],
  "channelId": null
}