{
  "song": "菫青幻想曲〜Fantasy of Iolite〜",
  "contentId": "sm20726442",
  "title": "【ミク GUMI Lily いろは】「 菫青幻想曲～Fantasy of Iolite～」オリジナル曲",
  "commentCounter": 1216,
  "lengthSeconds": 285,
  "likeCounter": 31,
  "mylistCounter": 2150,
  "rank": 664,
  "startTime": "2013-04-29T11:04:02+09:00",
  "thumbnailUrl": "https://nicovideo.cdn.nimg.jp/thumbnails/20726442/20726442",
  "userId": 2393707,
  "viewCounter": 57079,
  "artist": [
    "natsuP"
  ],
  "tags": [
    "VOCALOID",
    "SCL_Project",
    "初音ミク",
    "GUMI",
    "lily",
    "猫村いろは",
    "natsuP",
    "春アキ",
    "菫青幻想曲～Fantasy_of_Iolite～",
    "VOCALOIDオリジナル曲",
    "機動歌姫ヴォーカリオン"
  ],
  "channelId": null
}