{
  "song": "flower of sorrow",
  "contentId": "sm21209738",
  "title": "【初音ミク】flower of sorrow【オリジナル曲】",
  "commentCounter": 1739,
  "lengthSeconds": 261,
  "likeCounter": 84,
  "mylistCounter": 4630,
  "rank": 372,
  "startTime": "2013-06-27T19:00:00+09:00",
  "thumbnailUrl": "https://nicovideo.cdn.nimg.jp/thumbnails/21209738/21209738",
  "userId": 308936,
  "viewCounter": 162430,
  "artist": [
    "OSTER project"
  ],
  "tags": [
    "VOCALOID",
    "初音ミク",
    "VOCALOID殿堂入り",
    "DAM配信中",
    "ミクオリジナル曲",
    "OSTER_project",
    "flower_of_sorrow",
    "ダルビッシュP",
    "もか"
  ],
  "channelId": null
}