{
  "song": "ソイネ",
  "contentId": "sm22757095",
  "title": "ソイネ／164 feat.GUMI",
  "commentCounter": 928,
  "lengthSeconds": 223,
  "likeCounter": 36,
  "mylistCounter": 2505,
  "rank": 402,
  "startTime": "2014-01-27T20:00:00+09:00",
  "thumbnailUrl": "https://nicovideo.cdn.nimg.jp/thumbnails/22757095/22757095",
  "userId": 582229,
  "viewCounter": 85122,
  "artist": [
    "164"
  ],
  "tags": [
    "VOCALOID",
    "164",
    "房野聖",
    "GUMI",
    "ソイネ",
    "VOCAROCK",
    "Vocalofanatic収録曲",
    "GUMIオリジナル曲",
    "DAM&JOY配信中"
  ],
  "channelId": null
}