{
  "song": "荒ぶるマリンバ タカトコタン",
  "contentId": "sm23369433",
  "artist": [
    "オワタP"
  ],
  "channelId": null,
  "commentCounter": 2020,
  "lengthSeconds": 202,
  "likeCounter": 60,
  "mylistCounter": 1563,
  "startTime": "2014-04-20T11:55:00+09:00",
  "tags": [
    "VOCALOID",
    "オワタP",
    "夜宵",
    "鏡音リン",
    "鏡音レン",
    "荒ぶるマリンバ",
    "きのこたけのこ戦争",
    "演奏してみろ",
    "VOCALOID民族調曲",
    "鏡音オリジナル曲",
    "叩いてみろ"
  ],
  "thumbnailUrl": "https://nicovideo.cdn.nimg.jp/thumbnails/23369433/23369433",
  "title": "【鏡音リン、鏡音レン】荒ぶるマリンバ　タカトコタン【ガルナ/オワタP】",
  "userId": 1320776,
  "viewCounter": 69160,
  "rank": 581
}