{
  "song": "進捗どうですか！",
  "contentId": "sm24187254",
  "title": "【弱音ハク、亞北ネル】進捗どうですか！【ガルナ/オワタP】",
  "startTime": "2014-08-09T08:09:00+09:00",
  "userId": 1320776,
  "thumbnailUrl": "https://nicovideo.cdn.nimg.jp/thumbnails/24187254/24187254",
  "viewCounter": 307812,
  "mylistCounter": 6507,
  "likeCounter": 474,
  "commentCounter": 5237,
  "lengthSeconds": 208,
  "artist": [
    "オワタP"
  ],
  "tags": [
    "VOCALOID",
    "弱音ハク",
    "亞北ネル",
    "VOCALOID殿堂入り",
    "最後まで見るべき",
    "DAM&JOY配信中",
    "ゴミを見る目",
    "進捗どうですか！",
    "ドmホイホイ",
    "作業用bgm(上級者向け)",
    "8月9日はハクの日"
  ],
  "channelId": null,
  "rank": 171
}