{
  "song": "大正ロマンチック",
  "contentId": "sm30657082",
  "title": "【初音ミク】 大正ロマンチック 【オリジナルMV】",
  "commentCounter": 1884,
  "lengthSeconds": 278,
  "likeCounter": 361,
  "mylistCounter": 3178,
  "rank": 164,
  "startTime": "2017-02-18T20:00:00+09:00",
  "thumbnailUrl": "https://nicovideo.cdn.nimg.jp/thumbnails/30657082/30657082",
  "userId": 3343223,
  "viewCounter": 215013,
  "artist": [
    "40mP"
  ],
  "tags": [
    "VOCALOID",
    "初音ミク",
    "40mP",
    "大正ロマンチック",
    "ミクオリジナル曲",
    "VOCALOID殿堂入り",
    "かわいいミクうた",
    "お洒落なミクうた",
    "大正浪漫",
    "MUSIC_STUDY_PROJECT",
    "VOCALOID大正浪漫"
  ],
  "channelId": null
}