{
  "song": "新宿人魚姫",
  "contentId": "sm31635014",
  "title": "新宿人魚姫/Jille.Starz☆ Feat. GUMI",
  "commentCounter": 166,
  "lengthSeconds": 255,
  "likeCounter": 22,
  "mylistCounter": 380,
  "rank": 776,
  "startTime": "2017-07-26T19:00:00+09:00",
  "thumbnailUrl": "https://nicovideo.cdn.nimg.jp/thumbnails/31635014/31635014",
  "userId": 207175,
  "viewCounter": 17829,
  "artist": [
    "Jille.Starz☆"
  ],
  "tags": [
    "VOCALOID",
    "GUMI",
    "GUMIオリジナル曲",
    "Jille.Starz☆",
    "カザマ",
    "新宿人魚姫",
    "VOCALOID和風曲",
    "VOCALOID新宿入り"
  ],
  "channelId": null
}