{
  "song": "Mei Mei",
  "contentId": "sm33465330",
  "title": "Mei Mei / 初音ミク",
  "commentCounter": 3195,
  "lengthSeconds": 234,
  "likeCounter": 792,
  "mylistCounter": 4256,
  "rank": 111,
  "startTime": "2018-07-09T19:00:00+09:00",
  "thumbnailUrl": "https://nicovideo.cdn.nimg.jp/thumbnails/33465330/33465330",
  "userId": 865591,
  "viewCounter": 523602,
  "artist": [
    "ピノキオピー"
  ],
  "tags": [
    "VOCALOID",
    "初音ミク",
    "ピノキオピー",
    "Mei_Mei",
    "VOCALOID実写PV",
    "ミクオリジナル曲",
    "アイマイナちゃん",
    "どうしてちゃん",
    "VOCALOID殿堂入り",
    "寿司くらい好き",
    "初音ミク名曲リンク"
  ],
  "channelId": null
}