{
  "song": "700800を踊る我らが26で或る。",
  "contentId": "sm33457545",
  "title": "700800を踊る我らが26で或る。",
  "startTime": "2018-07-02T18:00:00+09:00",
  "userId": 45013355,
  "thumbnailUrl": "https://nicovideo.cdn.nimg.jp/thumbnails/33457545/33457545",
  "viewCounter": 159476,
  "mylistCounter": 1493,
  "likeCounter": 104,
  "commentCounter": 751,
  "lengthSeconds": 223,
  "artist": [
    "SLAVE.V-V-R"
  ],
  "tags": [
    "VOCALOID",
    "SLAVE.V-V-R",
    "初音ミク",
    "猫村いろは",
    "結月ゆかり",
    "JOYSOUND配信中",
    "スレイブ製菓(シリーズ)",
    "VOCALOID殿堂入り",
    "歌踊コレOK"
  ],
  "channelId": null,
  "rank": 261
}