{
  "song": "馬鹿みたいだ。",
  "contentId": "sm33323920",
  "title": "馬鹿みたいだ。 / IA [MV]",
  "startTime": "2018-06-06T18:00:00+09:00",
  "userId": 11040555,
  "thumbnailUrl": "https://nicovideo.cdn.nimg.jp/thumbnails/33323920/33323920",
  "viewCounter": 44546,
  "mylistCounter": 778,
  "likeCounter": 101,
  "commentCounter": 264,
  "lengthSeconds": 173,
  "artist": [
    "とうかさ"
  ],
  "tags": [
    "VOCALOID",
    "IAオリジナル曲",
    "IA_-ARIA_ON_THE_PLANETES-",
    "VOCALOIDオリジナル曲",
    "とうかさ",
    "NIX",
    "もっと評価されるべき",
    "VOCALOID実写PV",
    "馬鹿みたいだ。",
    "オルタナティブミック"
  ],
  "channelId": null,
  "rank": 425
}