{
  "song": "ぽっかり愛ノ謳",
  "contentId": "sm34831593",
  "title": "ぽっかり愛ノ謳／初音ミク",
  "commentCounter": 172,
  "lengthSeconds": 195,
  "likeCounter": 21,
  "mylistCounter": 199,
  "rank": 1130,
  "startTime": "2019-03-23T17:02:02+09:00",
  "thumbnailUrl": "https://nicovideo.cdn.nimg.jp/thumbnails/34831593/34831593.25384",
  "userId": 87790043,
  "viewCounter": 10808,
  "artist": [
    "すず"
  ],
  "tags": [
    "VOCALOID",
    "初音ミク",
    "VOCALOIDオリジナル曲",
    "すず",
    "miyame",
    "すず(ボカロP)",
    "かわいいミクうた",
    "お洒落なミクうた",
    "ぽっかり愛ノ謳",
    "既存楽曲復活祭"
  ],
  "channelId": null
}