{
  "song": "哀 Luv U",
  "contentId": "sm35293909",
  "title": "哀 Luv U／mint*(薄荷キャンディP) feat.flower",
  "commentCounter": 114,
  "lengthSeconds": 220,
  "likeCounter": 61,
  "mylistCounter": 637,
  "rank": 497,
  "startTime": "2019-06-21T20:00:00+09:00",
  "thumbnailUrl": "https://nicovideo.cdn.nimg.jp/thumbnails/35293909/35293909.36887635",
  "userId": 6715970,
  "viewCounter": 56443,
  "artist": [
    "mint*"
  ],
  "tags": [
    "VOCALOID",
    "VOCALOIDオリジナル曲",
    "flower",
    "v_flowerオリジナル曲",
    "v_flower",
    "mint*",
    "攻(おさむ)",
    "翠葉",
    "もっと評価されるべき",
    "良調教"
  ],
  "channelId": null
}