{
  "song": "小説　夏と罰 (下)",
  "contentId": "sm35385941",
  "title": "小説　夏と罰 (下)　/  feat. 猫村いろは",
  "commentCounter": 240,
  "lengthSeconds": 225,
  "likeCounter": 348,
  "mylistCounter": 976,
  "rank": 339,
  "startTime": "2019-07-11T19:15:00+09:00",
  "thumbnailUrl": "https://nicovideo.cdn.nimg.jp/thumbnails/35385941/35385941.35285137",
  "userId": 52158359,
  "viewCounter": 152312,
  "artist": [
    "傘村トータ"
  ],
  "tags": [
    "VOCALOID",
    "猫村いろは",
    "いろはオリジナル曲",
    "傘村トータ",
    "小説__夏と罰_(下)",
    "ボカロバラード",
    "VOCALOID夏曲",
    "神調教",
    "魂実装済み",
    "ききいるいろはうた",
    "VOCALOID殿堂入り"
  ],
  "channelId": null
}