{
  "song": "サイコグラム",
  "contentId": "sm35513173",
  "title": "DECO*27 - サイコグラム feat. 初音ミク",
  "startTime": "2019-08-09T20:00:00+09:00",
  "userId": 811012,
  "thumbnailUrl": "https://nicovideo.cdn.nimg.jp/thumbnails/35513173/35513173.49985869",
  "viewCounter": 1110197,
  "mylistCounter": 6689,
  "likeCounter": 2080,
  "commentCounter": 8115,
  "lengthSeconds": 224,
  "artist": [
    "DECO*27"
  ],
  "tags": [
    "VOCALOID",
    "DECO*27",
    "初音ミク",
    "ミクオリジナル曲",
    "サイコグラム",
    "DAM&JOY配信中",
    "初音ミク名曲リンク",
    "VOCAROCK",
    "Rockwell",
    "VOCALOID伝説入り",
    "ヤンデロイド"
  ],
  "channelId": null,
  "rank": 49
}