{
  "song": "レナ",
  "contentId": "sm36283870",
  "title": "Chinozo 「レナ」 feat.MikU",
  "commentCounter": 511,
  "lengthSeconds": 173,
  "likeCounter": 606,
  "mylistCounter": 900,
  "rank": 343,
  "startTime": "2020-01-28T19:00:00+09:00",
  "thumbnailUrl": "https://nicovideo.cdn.nimg.jp/thumbnails/36283870/36283870.13878874",
  "userId": 55005244,
  "viewCounter": 100312,
  "artist": [
    "Chinozo"
  ],
  "tags": [
    "VOCALOID",
    "ミクオリジナル曲",
    "初音ミク",
    "VOCALOIDオリジナル曲",
    "Chinozo",
    "天通",
    "Yusuke_Tsuji",
    "レナ(Chinozo)",
    "お洒落なミクうた",
    "もっと評価されるべき",
    "VOCALOID殿堂入り"
  ],
  "channelId": null
}