{
  "song": "春嵐",
  "contentId": "sm36053074",
  "title": "春嵐 / 初音ミク",
  "startTime": "2019-12-07T12:02:02+09:00",
  "userId": 88786564,
  "thumbnailUrl": "https://nicovideo.cdn.nimg.jp/thumbnails/36053074/36053074.63093467",
  "viewCounter": 9227839,
  "mylistCounter": 37984,
  "likeCounter": 56933,
  "commentCounter": 9526,
  "lengthSeconds": 154,
  "artist": [
    "john"
  ],
  "tags": [
    "VOCALOID",
    "初音ミク",
    "john(ボカロP)",
    "春嵐(john)",
    "ミクオリジナル曲",
    "VOCALOIDデジタルロック",
    "ボカロP自作アニメーションMVリンク",
    "VOCALOID伝説入り",
    "VOCALOID神話入り直前",
    "初音ミク名曲リンク",
    "DAM&JOY配信中"
  ],
  "channelId": null,
  "rank": 4
}