{
  "song": "とある娼婦の恋",
  "contentId": "sm3777353",
  "title": "初音ミク+鏡音リンの百合ジナル曲６ とある娼婦の恋 -Full ver.-",
  "startTime": "2008-06-26T23:08:42+09:00",
  "userId": 1075175,
  "thumbnailUrl": "https://nicovideo.cdn.nimg.jp/thumbnails/3777353/3777353",
  "viewCounter": 238997,
  "mylistCounter": 3484,
  "likeCounter": 79,
  "commentCounter": 7489,
  "lengthSeconds": 245,
  "artist": [
    "デッドボールP"
  ],
  "tags": [
    "デッドボールP",
    "VOCALOID",
    "とある娼婦の恋",
    "初音ミク",
    "鏡音リン",
    "ミク×リンリンク",
    "VOCALOID殿堂入り",
    "vocaloid百合曲",
    "vocaloidデュエット曲",
    "vocaloidオリジナル曲",
    "限りなくアウトを超越したなにか"
  ],
  "channelId": null,
  "rank": 470
}