{
  "song": "天誅",
  "contentId": "sm37974374",
  "title": "天誅 / 香椎モイミ feat. 鏡音レン",
  "commentCounter": 238,
  "lengthSeconds": 192,
  "likeCounter": 448,
  "mylistCounter": 528,
  "rank": 546,
  "startTime": "2020-12-17T20:00:00+09:00",
  "thumbnailUrl": "https://nicovideo.cdn.nimg.jp/thumbnails/37974374/37974374.34231370",
  "userId": 86944362,
  "viewCounter": 67138,
  "artist": [
    "香椎モイミ"
  ],
  "tags": [
    "VOCALOID",
    "鏡音レン",
    "香椎モイミ",
    "Aza",
    "ろーまじん",
    "天誅（香椎モイミ）",
    "レンオリジナル曲",
    "お洒落なレンうた",
    "神調教",
    "鏡音レン名曲リンク",
    "VocaR&B"
  ],
  "channelId": null
}