{
  "song": "劣情ノート",
  "contentId": "sm38100592",
  "artist": [
    "志茉理寿"
  ],
  "channelId": null,
  "commentCounter": 142,
  "lengthSeconds": 240,
  "likeCounter": 309,
  "mylistCounter": 329,
  "startTime": "2021-01-10T19:06:02+09:00",
  "tags": [
    "VOCALOID",
    "GUMI",
    "GUMIオリジナル曲",
    "VOCALOIDオリジナル曲",
    "魂実装済み",
    "劣情ノート",
    "くられ",
    "志茉理寿",
    "ききいるGUMIうた",
    "お洒落なGUMIうた",
    "chippy"
  ],
  "thumbnailUrl": "https://nicovideo.cdn.nimg.jp/thumbnails/38100592/38100592.46305994",
  "title": "劣情ノート / 志茉理寿 feat.GUMI",
  "userId": 30193092,
  "viewCounter": 26234,
  "rank": 712
}