{
  "song": "アルトラエレジー",
  "contentId": "sm39926273",
  "title": "アルトラエレジー / Aqu3ra feat. 初音ミク with.GABULI",
  "commentCounter": 351,
  "lengthSeconds": 173,
  "likeCounter": 1212,
  "mylistCounter": 1090,
  "rank": 355,
  "startTime": "2022-01-21T19:03:00+09:00",
  "thumbnailUrl": "https://nicovideo.cdn.nimg.jp/thumbnails/39926273/39926273.48162434",
  "userId": 83706458,
  "viewCounter": 179470,
  "artist": [
    "Aqu3ra"
  ],
  "tags": [
    "VOCALOID",
    "初音ミク",
    "Aqu3ra",
    "GABULI",
    "アルトラエレジー",
    "ミクオリジナル曲",
    "にへ",
    "ZABI",
    "ポケット（絵師）",
    "クールなミクうた",
    "VOCALOID殿堂入り"
  ],
  "channelId": null
}