{
  "song": "火葬",
  "contentId": "sm39206579",
  "title": "『　　』 … GUMI",
  "commentCounter": 272,
  "lengthSeconds": 112,
  "likeCounter": 1250,
  "mylistCounter": 525,
  "rank": 480,
  "startTime": "2021-08-19T21:00:00+09:00",
  "thumbnailUrl": "https://nicovideo.cdn.nimg.jp/thumbnails/39206579/39206579.95334414",
  "userId": 35587934,
  "viewCounter": 47304,
  "artist": [
    "youまん"
  ],
  "tags": [
    "VOCALOID",
    "GUMI",
    "GUMIオリジナル曲",
    "youまん",
    "ボカロバラード",
    "『____』(youまん)",
    "ききいるGUMIうた",
    "VOCALOID無題曲リンク",
    "火葬",
    "神調教",
    "『火葬』(youまん)"
  ],
  "channelId": null
}