{
  "song": "シリカニバリルナ",
  "contentId": "sm40256852",
  "title": "シリカニバリルナ／じょるじん feat.鏡音レン",
  "commentCounter": 886,
  "lengthSeconds": 164,
  "likeCounter": 1606,
  "mylistCounter": 790,
  "rank": 470,
  "startTime": "2022-04-01T20:00:00+09:00",
  "thumbnailUrl": "https://nicovideo.cdn.nimg.jp/thumbnails/40256852/40256852.11538370",
  "userId": 8661831,
  "viewCounter": 184427,
  "artist": [
    "じょるじん"
  ],
  "tags": [
    "鏡音レン",
    "VOCALOID",
    "レンオリジナル曲",
    "シリカニバリルナ",
    "テナテル",
    "DAM&JOY配信中",
    "アルバート・フィッシュ",
    "レンの将来が不安になる動画",
    "VOCALOID幻想狂気曲リンク",
    "じょるじん(暗黒童話P)",
    "VOCALOID殿堂入り"
  ],
  "channelId": null
}