{
  "song": "先生、いいですか。",
  "contentId": "sm40328960",
  "title": "先生、いいですか。／feat.可不",
  "commentCounter": 1672,
  "lengthSeconds": 197,
  "likeCounter": 1085,
  "mylistCounter": 612,
  "rank": 584,
  "startTime": "2022-04-22T00:00:00+09:00",
  "thumbnailUrl": "https://nicovideo.cdn.nimg.jp/thumbnails/40328960/40328960.32998954",
  "userId": 120845857,
  "viewCounter": 139041,
  "artist": [
    "雨曇"
  ],
  "tags": [
    "ボカコレ2022春TOP100参加作品",
    "ボカコレ2022春ルーキー参加作品",
    "雨曇",
    "先生、いいですか。",
    "可不",
    "可不オリジナル曲",
    "音楽",
    "cevioオリジナル曲",
    "CeVIO殿堂入り",
    "VOCALOID",
    "ダークなぼかうた"
  ],
  "channelId": null
}