{
  "song": "黄昏を生きる",
  "contentId": "sm41991087",
  "title": "黄昏を生きる　/  feat. MEIKO",
  "commentCounter": 585,
  "lengthSeconds": 194,
  "likeCounter": 1499,
  "mylistCounter": 1042,
  "rank": 268,
  "startTime": "2023-03-26T21:00:00+09:00",
  "thumbnailUrl": "https://nicovideo.cdn.nimg.jp/thumbnails/41991087/41991087.63134252",
  "userId": 52158359,
  "viewCounter": 154586,
  "artist": [
    "傘村トータ"
  ],
  "tags": [
    "VOCALOID",
    "MEIKO",
    "MEIKOオリジナル曲",
    "黄昏を生きる",
    "傘村トータ",
    "晴天を穿つ",
    "ピアノMEIKO",
    "VOCALOID夕暮れ曲",
    "せつない姉さんは好きですか",
    "VOCALOID殿堂入り"
  ],
  "channelId": null
}