{
  "song": "メテオラ",
  "contentId": "sm42902149",
  "title": "Chinozo 「メテオラ」 feat.FloweR・KafU",
  "commentCounter": 266,
  "lengthSeconds": 192,
  "likeCounter": 1149,
  "mylistCounter": 512,
  "rank": 597,
  "startTime": "2023-10-18T20:00:00+09:00",
  "thumbnailUrl": "https://nicovideo.cdn.nimg.jp/thumbnails/42902149/42902149.32270029",
  "userId": 55005244,
  "viewCounter": 58044,
  "artist": [
    "Chinozo"
  ],
  "tags": [
    "VOCALOID",
    "Chinozo",
    "v_flower",
    "可不",
    "アルセチカ",
    "VOCALOID&CeVIOオリジナル曲",
    "メテオラ(Chinozo)",
    "CeVIO_AI",
    "かふらわー",
    "引きこもりP"
  ],
  "channelId": null
}