{
  "song": "円尾坂の仕立屋",
  "contentId": "sm9032932",
  "title": "【巡音ルカ】円尾坂の仕立屋【和風物語風オリジナル】",
  "startTime": "2009-12-08T05:58:30+09:00",
  "userId": 907343,
  "thumbnailUrl": "https://nicovideo.cdn.nimg.jp/thumbnails/9032932/9032932",
  "viewCounter": 1870305,
  "mylistCounter": 37684,
  "likeCounter": 2316,
  "commentCounter": 81706,
  "lengthSeconds": 394,
  "artist": [
    "悪ノP"
  ],
  "tags": [
    "VOCALOID",
    "巡音ルカ",
    "ルカオリジナル曲",
    "悪ノＰ",
    "七つの大罪シリーズ",
    "円尾坂の仕立屋",
    "VOCALOID伝説入り",
    "巡音ルカ名曲リンク",
    "ヤンデロイド",
    "DAM&JOY配信中",
    "VOCALOID和風曲"
  ],
  "channelId": null,
  "rank": 44
}